mailman_web-0.0.9.dist-info/METADATA
mailman_web-0.0.9.dist-info/WHEEL
mailman_web-0.0.9.dist-info/entry_points.txt
mailman_web-0.0.9.dist-info/licenses/LICENSE.txt
mailman_web/__init__.py
mailman_web/manage.py
mailman_web/settings/__init__.py
mailman_web/settings/base.py
mailman_web/settings/dev.py
mailman_web/settings/mailman.py
mailman_web/tests/__init__.py
mailman_web/tests/settings.py
mailman_web/tests/test_basic.py
mailman_web/urls.py
mailman_web/wsgi.py
mailman_web-0.0.9.dist-info/RECORD
