Metadata-Version: 2.1
Name: mailman-web
Version: 0.0.9
Summary: Mailman 3 Web interface.
Author-Email: Mailman Developers <mailman-developers@python.org>
License: GPLv3
Classifier: Development Status :: 4 - Beta
Classifier: Framework :: Django
Classifier: Intended Audience :: System Administrators
Classifier: License :: OSI Approved :: GNU General Public License v3 or later (GPLv3+)
Classifier: Operating System :: POSIX
Classifier: Programming Language :: Python :: 3
Classifier: Topic :: Internet :: WWW/HTTP :: WSGI :: Application
Project-URL: Homepage, https://gitlab.com/mailman/mailman-web
Requires-Python: >=3.9
Requires-Dist: django<4.3,>=4.0
Requires-Dist: hyperkitty
Requires-Dist: postorius
Requires-Dist: whoosh
